{
  "expire_suffix_list": [".scn.m"],
  "file_info": {
    "all_a01.txt": [0,41552],
    "all_a02.txt": [41552,17385],
    "all_a03.txt": [58937,23201],
    "all_a04.txt": [82138,42976],
    "all_a05.txt": [125114,57095],
    "all_a06.txt": [182209,34811],
    "all_b01.txt": [217020,19701],
    "all_b02.txt": [236721,40349],
    "all_b03.txt": [277070,24667],
    "all_b04.txt": [301737,34901],
    "all_b05.txt": [336638,57761],
    "all_c01.txt": [394399,88119],
    "all_c02.txt": [482518,110157],
    "all_d01.txt": [592675,71947],
    "all_d02.txt": [664622,8472],
    "all_d03.txt": [673094,7963],
    "all_d04.txt": [681057,26222],
    "all_d05.txt": [707279,25630],
    "all_d06.txt": [732909,38532],
    "all_ed00.txt": [771441,1466],
    "all_end01.txt": [772907,32645],
    "all_end02.txt": [805552,32444],
    "charvoice": [837996,1283],
    "chino_a01.txt": [839279,44569],
    "chino_a02.txt": [883848,32214],
    "chino_a03.txt": [916062,2886],
    "chino_a04.txt": [918948,27178],
    "chino_a05.txt": [946126,19823],
    "chino_a06.txt": [965949,21421],
    "chino_a07.txt": [987370,6293],
    "chino_a08.txt": [993663,26654],
    "chino_a09.txt": [1020317,18939],
    "chino_a10.txt": [1039256,18377],
    "chino_b01.txt": [1057633,32137],
    "chino_b02.txt": [1089770,23554],
    "chino_b03.txt": [1113324,6909],
    "chino_b04.txt": [1120233,41096],
    "chino_b05.txt": [1161329,16297],
    "chino_b06.txt": [1177626,73064],
    "chino_b07.txt": [1250690,35935],
    "chino_c01.txt": [1286625,16253],
    "chino_c02.txt": [1302878,16718],
    "chino_c03.txt": [1319596,37620],
    "chino_c04.txt": [1357216,20317],
    "chino_c05.txt": [1377533,35699],
    "chino_c06.txt": [1413232,16642],
    "chino_c07.txt": [1429874,55173],
    "chino_d01.txt": [1485047,14266],
    "chino_d02.txt": [1499313,35263],
    "chino_d03.txt": [1534576,22215],
    "chino_d04.txt": [1556791,16324],
    "chino_d05.txt": [1573115,21718],
    "chino_d06.txt": [1594833,22190],
    "chino_d07.txt": [1617023,45056],
    "chino_d08.txt": [1662079,18772],
    "chino_d09.txt": [1680851,67546],
    "chino_ed00.txt": [1748397,1467],
    "chino_ed01.txt": [1749864,31956],
    "chino_ed02.txt": [1781820,26476],
    "chiya_a01.txt": [1808296,5276],
    "chiya_a02.txt": [1813572,36793],
    "chiya_a03.txt": [1850365,7834],
    "chiya_a04.txt": [1858199,23859],
    "chiya_a05.txt": [1882058,22647],
    "chiya_a06.txt": [1904705,25495],
    "chiya_a07.txt": [1930200,24047],
    "chiya_a08.txt": [1954247,42043],
    "chiya_b01.txt": [1996290,19997],
    "chiya_b02.txt": [2016287,30755],
    "chiya_b03.txt": [2047042,36042],
    "chiya_b04.txt": [2083084,27512],
    "chiya_b05.txt": [2110596,47637],
    "chiya_b06.txt": [2158233,35894],
    "chiya_b07.txt": [2194127,66827],
    "chiya_c01.txt": [2260954,57947],
    "chiya_c02.txt": [2318901,67576],
    "chiya_c03.txt": [2386477,15941],
    "chiya_c04.txt": [2402418,29272],
    "chiya_c05.txt": [2431690,34305],
    "chiya_d01.txt": [2465995,68695],
    "chiya_d02.txt": [2534690,31328],
    "chiya_d03.txt": [2566018,88552],
    "chiya_d04.txt": [2654570,27939],
    "chiya_d05.txt": [2682509,27615],
    "chiya_ed00.txt": [2710124,1465],
    "chiya_ed01.txt": [2711589,44610],
    "chiya_ed02.txt": [2756199,49442],
    "classlist": [2805641,1986],
    "date.ks": [2807627,3918],
    "day.ks": [2811545,5866],
    "filelist": [2817411,4517],
    "flyer.ks": [2821928,7461],
    "flyer_chino_a0.txt": [2829389,7698],
    "flyer_chino_a1.txt": [2837087,19540],
    "flyer_chino_a2.txt": [2856627,15077],
    "flyer_chino_a3.txt": [2871704,18937],
    "flyer_chino_a4.txt": [2890641,7665],
    "flyer_chino_b0.txt": [2898306,7671],
    "flyer_chino_b1.txt": [2905977,18776],
    "flyer_chino_b2.txt": [2924753,20413],
    "flyer_chino_b3.txt": [2945166,18570],
    "flyer_chino_b4.txt": [2963736,7671],
    "flyer_chino_c0.txt": [2971407,7664],
    "flyer_chino_c1.txt": [2979071,20646],
    "flyer_chino_c2.txt": [2999717,21710],
    "flyer_chino_c3.txt": [3021427,19958],
    "flyer_chino_c4.txt": [3041385,7703],
    "flyer_chino_d0.txt": [3049088,7704],
    "flyer_chino_d1.txt": [3056792,18455],
    "flyer_chino_d2.txt": [3075247,19460],
    "flyer_chino_d3.txt": [3094707,16345],
    "flyer_chino_d4.txt": [3111052,7700],
    "flyer_chino_e0.txt": [3118752,7705],
    "flyer_chino_e1.txt": [3126457,17496],
    "flyer_chino_e2.txt": [3143953,18368],
    "flyer_chino_e3.txt": [3162321,18502],
    "flyer_chino_e4.txt": [3180823,7704],
    "flyer_chino_f0.txt": [3188527,7707],
    "flyer_chino_f1.txt": [3196234,16358],
    "flyer_chino_f2.txt": [3212592,20499],
    "flyer_chino_f3.txt": [3233091,20806],
    "flyer_chino_f4.txt": [3253897,7703],
    "flyer_chino_g0.txt": [3261600,7705],
    "flyer_chino_g1.txt": [3269305,19440],
    "flyer_chino_g2.txt": [3288745,18796],
    "flyer_chino_g3.txt": [3307541,19475],
    "flyer_chino_g4.txt": [3327016,7702],
    "flyer_chino_h0.txt": [3334718,7708],
    "flyer_chino_h1.txt": [3342426,20352],
    "flyer_chino_h2.txt": [3362778,22646],
    "flyer_chino_h3.txt": [3385424,23426],
    "flyer_chino_h4.txt": [3408850,7703],
    "flyer_chino_i0.txt": [3416553,7706],
    "flyer_chino_i1.txt": [3424259,19991],
    "flyer_chino_i2.txt": [3444250,14814],
    "flyer_chino_i3.txt": [3459064,23356],
    "flyer_chino_i4.txt": [3482420,7706],
    "flyer_chino_j0.txt": [3490126,7709],
    "flyer_chino_j1.txt": [3497835,17676],
    "flyer_chino_j2.txt": [3515511,18505],
    "flyer_chino_j3.txt": [3534016,14458],
    "flyer_chino_j4.txt": [3548474,7708],
    "flyer_chiya_a0.txt": [3556182,7918],
    "flyer_chiya_a1.txt": [3564100,18129],
    "flyer_chiya_a2.txt": [3582229,22542],
    "flyer_chiya_a3.txt": [3604771,17698],
    "flyer_chiya_a4.txt": [3622469,7914],
    "flyer_chiya_b0.txt": [3630383,7910],
    "flyer_chiya_b1.txt": [3638293,17761],
    "flyer_chiya_b2.txt": [3656054,17225],
    "flyer_chiya_b3.txt": [3673279,16206],
    "flyer_chiya_b4.txt": [3689485,7911],
    "flyer_chiya_c0.txt": [3697396,7908],
    "flyer_chiya_c1.txt": [3705304,19560],
    "flyer_chiya_c2.txt": [3724864,16803],
    "flyer_chiya_c3.txt": [3741667,20609],
    "flyer_chiya_c4.txt": [3762276,7902],
    "flyer_chiya_d0.txt": [3770178,7911],
    "flyer_chiya_d1.txt": [3778089,16172],
    "flyer_chiya_d2.txt": [3794261,17615],
    "flyer_chiya_d3.txt": [3811876,19950],
    "flyer_chiya_d4.txt": [3831826,7906],
    "flyer_chiya_e0.txt": [3839732,7908],
    "flyer_chiya_e1.txt": [3847640,15378],
    "flyer_chiya_e2.txt": [3863018,18114],
    "flyer_chiya_e3.txt": [3881132,18170],
    "flyer_chiya_e4.txt": [3899302,7905],
    "flyer_chiya_f0.txt": [3907207,7910],
    "flyer_chiya_f1.txt": [3915117,15478],
    "flyer_chiya_f2.txt": [3930595,18942],
    "flyer_chiya_f3.txt": [3949537,18331],
    "flyer_chiya_f4.txt": [3967868,7908],
    "flyer_chiya_g0.txt": [3975776,7914],
    "flyer_chiya_g1.txt": [3983690,18453],
    "flyer_chiya_g2.txt": [4002143,16056],
    "flyer_chiya_g3.txt": [4018199,18195],
    "flyer_chiya_g4.txt": [4036394,7910],
    "flyer_chiya_h0.txt": [4044304,7908],
    "flyer_chiya_h1.txt": [4052212,15588],
    "flyer_chiya_h2.txt": [4067800,18165],
    "flyer_chiya_h3.txt": [4085965,16463],
    "flyer_chiya_h4.txt": [4102428,7901],
    "flyer_chiya_i0.txt": [4110329,7912],
    "flyer_chiya_i1.txt": [4118241,18172],
    "flyer_chiya_i2.txt": [4136413,15564],
    "flyer_chiya_i3.txt": [4151977,17576],
    "flyer_chiya_i4.txt": [4169553,7906],
    "flyer_chiya_j0.txt": [4177459,7909],
    "flyer_chiya_j1.txt": [4185368,16687],
    "flyer_chiya_j2.txt": [4202055,17033],
    "flyer_chiya_j3.txt": [4219088,19025],
    "flyer_chiya_j4.txt": [4238113,7908],
    "flyer_rize_a0.txt": [4246021,7664],
    "flyer_rize_a1.txt": [4253685,16260],
    "flyer_rize_a2.txt": [4269945,18993],
    "flyer_rize_a3.txt": [4288938,17220],
    "flyer_rize_a4.txt": [4306158,7667],
    "flyer_rize_b0.txt": [4313825,7667],
    "flyer_rize_b1.txt": [4321492,18266],
    "flyer_rize_b2.txt": [4339758,21257],
    "flyer_rize_b3.txt": [4361015,22774],
    "flyer_rize_b4.txt": [4383789,7664],
    "flyer_rize_c0.txt": [4391453,7661],
    "flyer_rize_c1.txt": [4399114,15907],
    "flyer_rize_c2.txt": [4415021,16697],
    "flyer_rize_c3.txt": [4431718,19075],
    "flyer_rize_c4.txt": [4450793,7662],
    "flyer_rize_d0.txt": [4458455,7670],
    "flyer_rize_d1.txt": [4466125,21634],
    "flyer_rize_d2.txt": [4487759,19362],
    "flyer_rize_d3.txt": [4507121,19398],
    "flyer_rize_d4.txt": [4526519,7662],
    "flyer_rize_e0.txt": [4534181,7667],
    "flyer_rize_e1.txt": [4541848,18923],
    "flyer_rize_e2.txt": [4560771,19474],
    "flyer_rize_e3.txt": [4580245,17493],
    "flyer_rize_e4.txt": [4597738,7661],
    "flyer_rize_f0.txt": [4605399,7660],
    "flyer_rize_f1.txt": [4613059,17928],
    "flyer_rize_f2.txt": [4630987,19867],
    "flyer_rize_f3.txt": [4650854,15177],
    "flyer_rize_f4.txt": [4666031,7663],
    "flyer_rize_g0.txt": [4673694,7665],
    "flyer_rize_g1.txt": [4681359,16365],
    "flyer_rize_g2.txt": [4697724,15449],
    "flyer_rize_g3.txt": [4713173,15641],
    "flyer_rize_g4.txt": [4728814,7664],
    "flyer_rize_h0.txt": [4736478,7658],
    "flyer_rize_h1.txt": [4744136,19462],
    "flyer_rize_h2.txt": [4763598,16994],
    "flyer_rize_h3.txt": [4780592,19372],
    "flyer_rize_h4.txt": [4799964,7667],
    "flyer_rize_i0.txt": [4807631,7668],
    "flyer_rize_i1.txt": [4815299,17967],
    "flyer_rize_i2.txt": [4833266,17922],
    "flyer_rize_i3.txt": [4851188,20954],
    "flyer_rize_i4.txt": [4872142,7661],
    "flyer_rize_j0.txt": [4879803,7662],
    "flyer_rize_j1.txt": [4887465,13888],
    "flyer_rize_j2.txt": [4901353,16405],
    "flyer_rize_j3.txt": [4917758,20673],
    "flyer_rize_j4.txt": [4938431,7663],
    "flyer_syaro_a0.txt": [4946094,8078],
    "flyer_syaro_a1.txt": [4954172,18467],
    "flyer_syaro_a2.txt": [4972639,17550],
    "flyer_syaro_a3.txt": [4990189,21269],
    "flyer_syaro_a4.txt": [5011458,7983],
    "flyer_syaro_b0.txt": [5019441,7987],
    "flyer_syaro_b1.txt": [5027428,16161],
    "flyer_syaro_b2.txt": [5043589,15374],
    "flyer_syaro_b3.txt": [5058963,20230],
    "flyer_syaro_b4.txt": [5079193,7986],
    "flyer_syaro_c0.txt": [5087179,7986],
    "flyer_syaro_c1.txt": [5095165,16872],
    "flyer_syaro_c2.txt": [5112037,20346],
    "flyer_syaro_c3.txt": [5132383,17049],
    "flyer_syaro_c4.txt": [5149432,7983],
    "flyer_syaro_d0.txt": [5157415,7988],
    "flyer_syaro_d1.txt": [5165403,17364],
    "flyer_syaro_d2.txt": [5182767,18519],
    "flyer_syaro_d3.txt": [5201286,19040],
    "flyer_syaro_d4.txt": [5220326,7984],
    "flyer_syaro_e0.txt": [5228310,7991],
    "flyer_syaro_e1.txt": [5236301,17541],
    "flyer_syaro_e2.txt": [5253842,15614],
    "flyer_syaro_e3.txt": [5269456,17479],
    "flyer_syaro_e4.txt": [5286935,7979],
    "flyer_syaro_f0.txt": [5294914,7985],
    "flyer_syaro_f1.txt": [5302899,18288],
    "flyer_syaro_f2.txt": [5321187,16429],
    "flyer_syaro_f3.txt": [5337616,19553],
    "flyer_syaro_f4.txt": [5357169,7982],
    "flyer_syaro_g0.txt": [5365151,7986],
    "flyer_syaro_g1.txt": [5373137,20959],
    "flyer_syaro_g2.txt": [5394096,16682],
    "flyer_syaro_g3.txt": [5410778,21315],
    "flyer_syaro_g4.txt": [5432093,7978],
    "flyer_syaro_h0.txt": [5440071,7982],
    "flyer_syaro_h1.txt": [5448053,18583],
    "flyer_syaro_h2.txt": [5466636,18374],
    "flyer_syaro_h3.txt": [5485010,15721],
    "flyer_syaro_h4.txt": [5500731,7986],
    "flyer_syaro_i0.txt": [5508717,7988],
    "flyer_syaro_i1.txt": [5516705,18079],
    "flyer_syaro_i2.txt": [5534784,16690],
    "flyer_syaro_i3.txt": [5551474,15293],
    "flyer_syaro_i4.txt": [5566767,7980],
    "flyer_syaro_j0.txt": [5574747,7987],
    "flyer_syaro_j1.txt": [5582734,17666],
    "flyer_syaro_j2.txt": [5600400,17629],
    "flyer_syaro_j3.txt": [5618029,20252],
    "flyer_syaro_j4.txt": [5638281,7985],
    "flyerhap_chino_a.txt": [5646266,37270],
    "flyerhap_chino_b.txt": [5683536,32006],
    "flyerhap_chino_c.txt": [5715542,45720],
    "flyerhap_chino_d.txt": [5761262,26559],
    "flyerhap_chino_e.txt": [5787821,44359],
    "flyerhap_chino_f.txt": [5832180,42876],
    "flyerhap_chino_g.txt": [5875056,32127],
    "flyerhap_chino_h.txt": [5907183,37248],
    "flyerhap_chino_i.txt": [5944431,33852],
    "flyerhap_chino_j.txt": [5978283,30931],
    "flyerhap_chiya_a.txt": [6009214,44289],
    "flyerhap_chiya_b.txt": [6053503,30410],
    "flyerhap_chiya_c.txt": [6083913,34365],
    "flyerhap_chiya_d.txt": [6118278,39153],
    "flyerhap_chiya_e.txt": [6157431,24656],
    "flyerhap_chiya_f.txt": [6182087,34372],
    "flyerhap_chiya_g.txt": [6216459,27579],
    "flyerhap_chiya_h.txt": [6244038,35090],
    "flyerhap_chiya_i.txt": [6279128,23493],
    "flyerhap_chiya_j.txt": [6302621,33566],
    "flyerhap_rize_a.txt": [6336187,30372],
    "flyerhap_rize_b.txt": [6366559,28821],
    "flyerhap_rize_c.txt": [6395380,29086],
    "flyerhap_rize_d.txt": [6424466,31274],
    "flyerhap_rize_e.txt": [6455740,40617],
    "flyerhap_rize_f.txt": [6496357,27983],
    "flyerhap_rize_g.txt": [6524340,25109],
    "flyerhap_rize_h.txt": [6549449,30927],
    "flyerhap_rize_i.txt": [6580376,34574],
    "flyerhap_rize_j.txt": [6614950,30188],
    "flyerhap_syaro_a.txt": [6645138,34004],
    "flyerhap_syaro_b.txt": [6679142,33389],
    "flyerhap_syaro_c.txt": [6712531,23542],
    "flyerhap_syaro_d.txt": [6736073,30021],
    "flyerhap_syaro_e.txt": [6766094,28938],
    "flyerhap_syaro_f.txt": [6795032,26743],
    "flyerhap_syaro_g.txt": [6821775,36394],
    "flyerhap_syaro_h.txt": [6858169,33340],
    "flyerhap_syaro_i.txt": [6891509,36784],
    "flyerhap_syaro_j.txt": [6928293,29239],
    "holiday.ks": [6957532,4313],
    "kigae.ks": [6961845,3883],
    "main_a01.txt": [6965728,24660],
    "main_a02.txt": [6990388,32320],
    "main_a03.txt": [7022708,46190],
    "main_a04.txt": [7068898,31381],
    "main_a05.txt": [7100279,59090],
    "main_a06.txt": [7159369,16438],
    "main_a07.txt": [7175807,7188],
    "main_b01.txt": [7182995,62850],
    "main_b02.txt": [7245845,41628],
    "main_b03.txt": [7287473,34628],
    "main_b04.txt": [7322101,32409],
    "main_b05.txt": [7354510,43436],
    "main_b06.txt": [7397946,42683],
    "main_b07.txt": [7440629,69963],
    "main_c01.txt": [7510592,73763],
    "main_d01.txt": [7584355,2662],
    "main_d02.txt": [7587017,2065],
    "main_d03.txt": [7589082,1906],
    "main_e01.txt": [7590988,2035],
    "main_e02.txt": [7593023,2084],
    "main_e03.txt": [7595107,2049],
    "main_e04.txt": [7597156,2038],
    "main_e05.txt": [7599194,2076],
    "main_ed.txt": [7601270,1140],
    "main_op.txt": [7602410,1261],
    "mainloop.ks": [7603671,3354],
    "move_a00.txt": [7607025,3154],
    "move_a01.txt": [7610179,39576],
    "move_a02.txt": [7649755,38018],
    "move_a03.txt": [7687773,34547],
    "move_a04.txt": [7722320,33190],
    "move_a05.txt": [7755510,32071],
    "move_a06.txt": [7787581,30812],
    "move_b00.txt": [7818393,3160],
    "move_b01.txt": [7821553,39707],
    "move_b02.txt": [7861260,32023],
    "move_b03.txt": [7893283,29868],
    "move_b04.txt": [7923151,25744],
    "move_b05.txt": [7948895,28825],
    "move_b06.txt": [7977720,36545],
    "move_c00.txt": [8014265,3196],
    "move_c01.txt": [8017461,31131],
    "move_c02.txt": [8048592,32392],
    "move_c03.txt": [8080984,36794],
    "move_c04.txt": [8117778,37335],
    "move_c05.txt": [8155113,26678],
    "move_c06.txt": [8181791,35871],
    "move_d00.txt": [8217662,3152],
    "move_d01.txt": [8220814,32859],
    "move_d02.txt": [8253673,37465],
    "move_d03.txt": [8291138,24385],
    "move_d04.txt": [8315523,35232],
    "move_d05.txt": [8350755,34970],
    "move_d06.txt": [8385725,33937],
    "move_e00.txt": [8419662,3170],
    "move_e01.txt": [8422832,31811],
    "move_e02.txt": [8454643,34207],
    "move_e03.txt": [8488850,31510],
    "move_e04.txt": [8520360,34550],
    "move_e05.txt": [8554910,30300],
    "move_e06.txt": [8585210,28442],
    "move_f00.txt": [8613652,3293],
    "move_f01.txt": [8616945,29112],
    "move_f02.txt": [8646057,36596],
    "move_f03.txt": [8682653,33506],
    "move_f04.txt": [8716159,30601],
    "move_f05.txt": [8746760,33480],
    "move_f06.txt": [8780240,37394],
    "pajamas_chino_01.txt": [8817634,17214],
    "pajamas_chino_02.txt": [8834848,14372],
    "pajamas_chino_03.txt": [8849220,13797],
    "pajamas_chiya_01.txt": [8863017,18784],
    "pajamas_chiya_02.txt": [8881801,17943],
    "pajamas_chiya_03.txt": [8899744,15923],
    "pajamas_main_01.txt": [8915667,65056],
    "pajamas_main_02.txt": [8980723,56476],
    "pajamas_main_03.txt": [9037199,52569],
    "pajamas_rize_01.txt": [9089768,16352],
    "pajamas_rize_02.txt": [9106120,16027],
    "pajamas_rize_03.txt": [9122147,18296],
    "pajamas_syaro_01.txt": [9140443,17220],
    "pajamas_syaro_02.txt": [9157663,16536],
    "pajamas_syaro_03.txt": [9174199,19266],
    "rize_a01.txt": [9193465,28781],
    "rize_a02.txt": [9222246,7560],
    "rize_a03.txt": [9229806,33673],
    "rize_a04.txt": [9263479,43157],
    "rize_a05.txt": [9306636,38111],
    "rize_a06.txt": [9344747,34638],
    "rize_a07.txt": [9379385,30225],
    "rize_b01.txt": [9409610,45489],
    "rize_b02.txt": [9455099,16848],
    "rize_b03.txt": [9471947,19000],
    "rize_b04.txt": [9490947,21650],
    "rize_b05.txt": [9512597,23236],
    "rize_b06.txt": [9535833,18947],
    "rize_c01.txt": [9554780,52985],
    "rize_c02.txt": [9607765,13727],
    "rize_c03.txt": [9621492,18974],
    "rize_c04.txt": [9640466,41614],
    "rize_c05.txt": [9682080,31113],
    "rize_d01.txt": [9713193,6527],
    "rize_d02.txt": [9719720,35847],
    "rize_d03.txt": [9755567,50715],
    "rize_d04.txt": [9806282,5525],
    "rize_d05.txt": [9811807,37309],
    "rize_d06.txt": [9849116,5028],
    "rize_d07.txt": [9854144,28577],
    "rize_d08.txt": [9882721,4266],
    "rize_d09.txt": [9886987,41559],
    "rize_ed00.txt": [9928546,1464],
    "rize_end01.txt": [9930010,35478],
    "rize_end02.txt": [9965488,32759],
    "scenelist": [9998247,106014],
    "shop.ks": [10104261,2806],
    "syaro_a01.txt": [10107067,13270],
    "syaro_a02.txt": [10120337,31556],
    "syaro_a03.txt": [10151893,44313],
    "syaro_a04.txt": [10196206,14039],
    "syaro_a05.txt": [10210245,41869],
    "syaro_a06.txt": [10252114,35723],
    "syaro_a07.txt": [10287837,4941],
    "syaro_b01.txt": [10292778,7242],
    "syaro_b02.txt": [10300020,23167],
    "syaro_b03.txt": [10323187,7073],
    "syaro_b04.txt": [10330260,30307],
    "syaro_b05.txt": [10360567,57857],
    "syaro_b06.txt": [10418424,27584],
    "syaro_b07.txt": [10446008,50609],
    "syaro_c01.txt": [10496617,26504],
    "syaro_c02.txt": [10523121,12764],
    "syaro_c03.txt": [10535885,51529],
    "syaro_c04.txt": [10587414,37982],
    "syaro_c05.txt": [10625396,20738],
    "syaro_d01.txt": [10646134,10233],
    "syaro_d02.txt": [10656367,31486],
    "syaro_d03.txt": [10687853,28109],
    "syaro_d04.txt": [10715962,29940],
    "syaro_d05.txt": [10745902,26801],
    "syaro_d06.txt": [10772703,24316],
    "syaro_d07.txt": [10797019,25588],
    "syaro_d08.txt": [10822607,44896],
    "syaro_ed00.txt": [10867503,1466],
    "syaro_end01.txt": [10868969,38078],
    "syaro_end02.txt": [10907047,36045],
    "test.ks": [10943092,20143],
    "tutorial_01.txt": [10963235,6786],
    "tutorial_02.txt": [10970021,15199],
    "visit.ks": [10985220,2311],
    "visit_aoyama_01.txt": [10987531,48507],
    "visit_aoyama_02.txt": [11036038,49246],
    "visit_aoyama_03.txt": [11085284,41256],
    "visit_chino_01.txt": [11126540,34193],
    "visit_chino_02.txt": [11160733,32627],
    "visit_chino_03.txt": [11193360,36782],
    "visit_chiya_01.txt": [11230142,28332],
    "visit_chiya_02.txt": [11258474,31805],
    "visit_chiya_03.txt": [11290279,49230],
    "visit_mame_01.txt": [11339509,46051],
    "visit_mame_02.txt": [11385560,42951],
    "visit_mame_03.txt": [11428511,42723],
    "visit_rize_01.txt": [11471234,39218],
    "visit_rize_02.txt": [11510452,33665],
    "visit_rize_03.txt": [11544117,39927],
    "visit_syaro_01.txt": [11584044,36749],
    "visit_syaro_02.txt": [11620793,40177],
    "visit_syaro_03.txt": [11660970,41597]
  },
  "id": "archive",
  "version": 1.0
}